metadata_chatbot/__init__.py
metadata_chatbot/models.py
metadata_chatbot/streamlit_app.py
metadata_chatbot/tools.py
metadata_chatbot/utils.py
metadata_chatbot/GAMER/_init_.py
metadata_chatbot/GAMER/workflow.py
metadata_chatbot/QC_portal/summary_generation.py
metadata_chatbot/evaluations/async_evaluator.py
metadata_chatbot/evaluations/benchmarks.py
metadata_chatbot/evaluations/anthropic/anthropic_eval.py
metadata_chatbot/evaluations/anthropic/anthropic_mongodb_eval.py
metadata_chatbot/evaluations/anthropic/anthropic_python_eval.py
metadata_chatbot/evaluations/anthropic/mongodb_anthropic.py
metadata_chatbot/evaluations/anthropic/nodes.py
metadata_chatbot/evaluations/anthropic/python_gen.py
metadata_chatbot/evaluations/anthropic/workflow.py
metadata_chatbot/evaluations/bedrock/bedrock_eval.py
metadata_chatbot/evaluations/bedrock/bedrock_mongodb_eval.py
metadata_chatbot/evaluations/bedrock/mongodb_bedrock.py
metadata_chatbot/evaluations/bedrock/workflow.py
metadata_chatbot/evaluations/benchmark_files/eval_benchmark_4_14_25.csv
metadata_chatbot/evaluations/benchmark_files/eval_benchmark_4_3_25.csv
metadata_chatbot/evaluations/benchmark_files/eval_benchmark_4_9_25.csv
metadata_chatbot/evaluations/benchmark_files/stats.ipynb
metadata_chatbot/evaluations/evals_all/anthropic_evals.csv
metadata_chatbot/evaluations/evals_all/anthropic_evals_4_10.csv
metadata_chatbot/evaluations/evals_all/bedrock_evals.csv
metadata_chatbot/evaluations/evals_all/bedrock_evals_4_10.csv
metadata_chatbot/evaluations/evals_all/final_bedrock_evals.csv
metadata_chatbot/evaluations/evals_all/gamer_eval_4_10.ipynb
metadata_chatbot/evaluations/evals_mongodb/anthropic_mongodb_evals.csv
metadata_chatbot/evaluations/evals_mongodb/bedrock_mongodb_evals.csv
metadata_chatbot/evaluations/evals_mongodb/bedrock_mongodb_evals_4_10.csv
metadata_chatbot/evaluations/evals_mongodb/bedrock_mongodb_evals_4_14.csv
metadata_chatbot/evaluations/evals_mongodb/bedrock_mongodb_evals_4_15.csv
metadata_chatbot-0.5.1.dist-info/licenses/LICENSE
metadata_chatbot-0.5.1.dist-info/METADATA
metadata_chatbot-0.5.1.dist-info/WHEEL
metadata_chatbot-0.5.1.dist-info/top_level.txt
metadata_chatbot-0.5.1.dist-info/RECORD
