Metadata-Version: 2.4
Name: metadata-chatbot
Version: 0.5.1
Summary: Generated from aind-library-template
Author: Allen Institute for Neural Dynamics
License: MIT
Classifier: Programming Language :: Python :: 3
Requires-Python: >=3.11
License-File: LICENSE
Requires-Dist: aind-data-access-api[full]>=0.15.0
Requires-Dist: boto3
Requires-Dist: langchain-aws
Requires-Dist: langchain_core
Requires-Dist: langchain
Requires-Dist: langchain_experimental
Requires-Dist: langgraph
Requires-Dist: sentence_transformers
Requires-Dist: langchain_anthropic
Provides-Extra: dev
Requires-Dist: black; extra == "dev"
Requires-Dist: coverage; extra == "dev"
Requires-Dist: flake8; extra == "dev"
Requires-Dist: interrogate; extra == "dev"
Requires-Dist: isort; extra == "dev"
Requires-Dist: Sphinx; extra == "dev"
Requires-Dist: furo; extra == "dev"
Dynamic: license-file
